asdf_transform_schemas/__init__.py
asdf_transform_schemas/_version.py
asdf_transform_schemas/integration.py
asdf_transform_schemas/resources/asdf-format.org/manifests/transform-1.0.0.yaml
asdf_transform_schemas/resources/asdf-format.org/manifests/transform-1.1.0.yaml
asdf_transform_schemas/resources/asdf-format.org/manifests/transform-1.2.0.yaml
asdf_transform_schemas/resources/asdf-format.org/manifests/transform-1.3.0.yaml
asdf_transform_schemas/resources/asdf-format.org/manifests/transform-1.4.0.yaml
asdf_transform_schemas/resources/asdf-format.org/manifests/transform-1.5.0.yaml
asdf_transform_schemas/resources/stsci.edu/schemas/add-1.0.0.yaml
asdf_transform_schemas/resources/stsci.edu/schemas/add-1.1.0.yaml
asdf_transform_schemas/resources/stsci.edu/schemas/add-1.2.0.yaml
asdf_transform_schemas/resources/stsci.edu/schemas/affine-1.0.0.yaml
asdf_transform_schemas/resources/stsci.edu/schemas/affine-1.1.0.yaml
asdf_transform_schemas/resources/stsci.edu/schemas/affine-1.2.0.yaml
asdf_transform_schemas/resources/stsci.edu/schemas/affine-1.3.0.yaml
asdf_transform_schemas/resources/stsci.edu/schemas/airy-1.0.0.yaml
asdf_transform_schemas/resources/stsci.edu/schemas/airy-1.1.0.yaml
asdf_transform_schemas/resources/stsci.edu/schemas/airy-1.2.0.yaml
asdf_transform_schemas/resources/stsci.edu/schemas/airy_disk2d-1.0.0.yaml
asdf_transform_schemas/resources/stsci.edu/schemas/arccosine1d-1.0.0.yaml
asdf_transform_schemas/resources/stsci.edu/schemas/arcsine1d-1.0.0.yaml
asdf_transform_schemas/resources/stsci.edu/schemas/arctangent1d-1.0.0.yaml
asdf_transform_schemas/resources/stsci.edu/schemas/blackbody-1.0.0.yaml
asdf_transform_schemas/resources/stsci.edu/schemas/bonne_equal_area-1.0.0.yaml
asdf_transform_schemas/resources/stsci.edu/schemas/bonne_equal_area-1.1.0.yaml
asdf_transform_schemas/resources/stsci.edu/schemas/bonne_equal_area-1.2.0.yaml
asdf_transform_schemas/resources/stsci.edu/schemas/bonne_equal_area-1.3.0.yaml
asdf_transform_schemas-0.4.0.dist-info/LICENSE
asdf_transform_schemas-0.4.0.dist-info/METADATA
asdf_transform_schemas-0.4.0.dist-info/WHEEL
asdf_transform_schemas-0.4.0.dist-info/entry_points.txt
asdf_transform_schemas-0.4.0.dist-info/top_level.txt
asdf_transform_schemas-0.4.0.dist-info/RECORD
