Metadata-Version: 2.1
Name: asdf-transform-schemas
Version: 0.4.0
Summary: ASDF schemas for transforms
Author-email: The ASDF Developers <help@stsci.edu>
License: Copyright (c) 2021 Association of Universities for Research in Astronomy.
Project-URL: tracker, https://github.com/asdf-format/asdf-transform-schemas/issues
Project-URL: documentation, https://asdf-transform-schemas.readthedocs.io/en/stable
Project-URL: repository, https://github.com/asdf-format/asdf-transform-schemas
Classifier: Programming Language :: Python
Classifier: Programming Language :: Python :: 3
Classifier: Programming Language :: Python :: 3.8
Classifier: Programming Language :: Python :: 3.9
Classifier: Programming Language :: Python :: 3.10
Classifier: Development Status :: 5 - Production/Stable
Requires-Python: >=3.8
License-File: LICENSE
Requires-Dist: asdf-standard>=1.0.1
Requires-Dist: importlib_resources>=3; python_version < "3.9"
Provides-Extra: docs
Requires-Dist: tomli; extra == "docs"
Requires-Dist: sphinx; extra == "docs"
Requires-Dist: sphinx-asdf>=0.1.3; extra == "docs"
Requires-Dist: sphinx-astropy; extra == "docs"
Requires-Dist: astropy>=5.0.4; extra == "docs"
Requires-Dist: graphviz; extra == "docs"
Requires-Dist: matplotlib; extra == "docs"
Requires-Dist: docutils; extra == "docs"
Requires-Dist: sphinx-rtd-theme; extra == "docs"
Provides-Extra: test
Requires-Dist: asdf>=2.8.0; extra == "test"
Requires-Dist: asdf-astropy; extra == "test"
Requires-Dist: scipy; extra == "test"
Requires-Dist: pytest; extra == "test"
